lightweight_genetic_algorithm/__init__.py
lightweight_genetic_algorithm/algorithm.py
lightweight_genetic_algorithm/crossover.py
lightweight_genetic_algorithm/mutation.py
lightweight_genetic_algorithm/population.py
lightweight_genetic_algorithm/selection.py
lightweight_genetic_algorithm-1.0.1.dist-info/METADATA
lightweight_genetic_algorithm-1.0.1.dist-info/WHEEL
lightweight_genetic_algorithm-1.0.1.dist-info/licenses/LICENSE
lightweight_genetic_algorithm-1.0.1.dist-info/RECORD
