Metadata-Version: 2.4
Name: lightweight_genetic_algorithm
Version: 1.0.1
Summary: An intuitive, flexible and efficient implementation of a genetic algorithm in Python
Project-URL: Homepage, https://github.com/JoseEliel/lightweight_genetic_algorithm
Project-URL: Documentation, https://lightweight-genetic-algorithm.readthedocs.io/
Author-email: Eliel Camargo-Molina <eliel@camargo-molina.com>, Jonas Wessén <jonas@jonas-wessen.com>
License-File: LICENSE
Classifier: Development Status :: 5 - Production/Stable
Classifier: License :: OSI Approved :: MIT License
Classifier: Programming Language :: Python :: 3.7
Classifier: Programming Language :: Python :: 3.8
Classifier: Programming Language :: Python :: 3.9
Classifier: Programming Language :: Python :: 3.10
Classifier: Programming Language :: Python :: 3.11
Classifier: Topic :: Scientific/Engineering :: Artificial Intelligence
Requires-Python: >=3.7
